{
	"new": {
		"": {
			"os": "",
			"android": "14.0",
			"release": "2024-09-19",
			"recovery": "",
			"fastboot": ""
		},
		" ": {
			"os": "",
			"android": "13.0",
			"release": "",
			"recovery": "",
			"fastboot": ""
		}
	},
	"ct": {
		"": {
			"os": "",
			"android": "14.0",
			"release": "2024-09-09",
			"recovery": "",
			"fastboot": "",
			"ctelecom": ""
		},
		" ": {
			"os": "",
			"android": "14.0",
			"release": "",
			"recovery": "",
			"fastboot": "",
			"ctelecom": ""
		}
	},
	"": {
		"os": "",
		"android": "15.0",
		"release": "2024-08-20",
		"recovery": "",
		"fastboot": "",
		"originrec": "",
		"originfb":""
	},
	" ": {
		"os": "",
		"android": "14.0",
		"release": "",
		"recovery": "",
		"fastboot": ""
	}
}
